<?xml version="1.0" encoding="utf-8"?>
<recette id="72976">
  <titre>Tarte à l'oignon rapide dont on dit du bien</titre>
  <type>Plat principal</type>
  <niveau>Très facile</niveau>
  <cout>Bon marché</cout>
  <ingredients>
    <p>pâte feuilletée toute prête</p>
    <p>6 oignons de taille moyenne</p>
    <p>huile d'olive (facultatif)</p>
    <p>3 tranches de fromage fondu pour sandwich (remplaçable par de la vache qui rit)</p>
    <p>2 poignées de gruyère râpé</p>
    <p>pointe de couteau de piment en poudre (facultatif)</p>
  </ingredients>
  <preparation>
  <![CDATA[
    Peler les oignons et les couper en fines tranches.
    Mettre les oignons dans un récipient allant au micro-ondes, ajouter un fond d'eau et recouvrir de film plastique.
    Faire cuire les oignons durant 8 à 10 minutes au micro-ondes à pleine puissance.
    (si la patience est une de vos vertus, il est possible de faire revenir les oignons à la poêle dans de l'huile d'olive jusqu'à ce qu'ils deviennent fondant)
    Etaler la pâte feuilletée dans un plat à tarte, la piquer et parsemer le fond de morceaux des tranches de fromage fondu.
    Ajouter les oignons cuits et égouttés, parsemer de la pointe de piment et recouvrir du gruyère râpé.
    Faire cuire à four chaud (200°C, thermostat 6-7) durant 30 bonnes minutes jusqu'à ce que la pâte soit cuite.
    MIAM !
    Si la pâte cuit moins vite que ne dore le gruyère, il suffit de couvrir la tarte de papier aluminium et de poursuivre la cuisson en baissant un peu le thermostat.
  ]]>
  </preparation>
</recette>
