<?xml version="1.0" encoding="utf-8"?>
<recette id="30285">
  <titre>Croque-monsieur au saumon</titre>
  <type>Plat principal</type>
  <niveau>Très facile</niveau>
  <cout>Moyen</cout>
  <ingredients>
    <p>8 tranches de pain de mie</p>
    <p>4 tranches de saumon fumé</p>
    <p>4 tranches de cheddar</p>
    <p>10 cL de crème fraîche épaisse (quantité selon votre goût)</p>
    <p>10 g de beurre</p>
  </ingredients>
  <preparation>
  <![CDATA[
    Beurrer les tranches de pain de mie.
    Sur le côté non beurré, mettre un peu de crème fraiche, puis une tranche de saumon fumé et une tranche de cheddar.
    Refermer le croque monsieur, et le fermer cuire quelques instants seulement dans l'appareil à croque monsieur (ou au grill, des deux côtés).Servir tiède, avec une salade verte.
  ]]>
  </preparation>
</recette>
