<?xml version="1.0" encoding="utf-8"?>
<recette id="167546">
  <titre>Vieille à la Bretonne (poisson)</titre>
  <type>Plat principal</type>
  <niveau>Facile</niveau>
  <cout>Moyen</cout>
  <ingredients>
    <p>Une vieille (ou carpe de mer)</p>
    <p>3 oignons</p>
    <p>5 pommes de terre</p>
    <p>1 bouquet garni (thym + laurier)</p>
    <p>Du sel</p>
    <p>Du poivre</p>
  </ingredients>
  <preparation>
  <![CDATA[
    Remplir une grande marmite d'eau salée et faire bouillir. Ajouter les oignons et pommes de terre en tranches fines et le bouquet garni. Faire bouillir 10 minutes environ.
    Ajouter la vieille tronçonnée en quatre. Rajouter du sel et du poivre. Laisser cuire à nouveau une dizaine de minutes.
    Il ne vous reste plus à servir les morceaux de vieille et le bouillon dans de belles assiettes à soupe.Ne pas hésiter à ajouter sur votre table, des petits croutons et de la rouille. Muscadet ou une bonne bière
  ]]>
  </preparation>
</recette>
