<?xml version="1.0" encoding="utf-8"?>
<recette id="80537">
  <titre>BOURRIDE A LA SETOISE</titre>
  <type>Plat principal</type>
  <niveau>Très facile</niveau>
  <cout>Moyen</cout>
  <ingredients>
    <p>6 queues de lotte surgelées</p>
    <p>2 ou 3 carottes</p>
    <p>2 poireaux</p>
    <p>2 coeurs de laitue</p>
    <p>1 branche de céleri</p>
    <p>1 petit oignon</p>
    <p>1 ail</p>
    <p>thym et laurier</p>
    <p>huile d'olive</p>
  </ingredients>
  <preparation>
  <![CDATA[
    Hacher menu les carottes, les poireaux, la laitue, le céleri, l'oignon et l'ail. 
    Mettre dans une cocotte avec du thym, du laurier et quelques cuillères à soupe d'huile d'olive.
    Laisser cuire une vingtaine de minutes.
    Faire à part un aïoli.
    Lorsque les légumes sont cuits, mettre les queues de lotte à cuire une dizaine de minutes.
    Faire griller à part des tranches de pain que l'on répandra sur le plat de service avec le poisson.
    Mélanger l'aïoli avec les légumes, et napper le poisson.
    Servir chaud.
     Rosé
  ]]>
  </preparation>
</recette>
