<?xml version="1.0" encoding="utf-8"?>
<recette id="11377">
  <titre>Mousse au chocolat blanc fondante</titre>
  <type>Dessert</type>
  <niveau>Moyennement difficile</niveau>
  <cout>Moyen</cout>
  <ingredients>
    <p>500 g de chocolat blanc</p>
    <p>40 cl de crème liquide</p>
    <p>10 blancs d'oeufs</p>
    <p>100 g de sucre glace</p>
    <p>copeaux de chocolat blanc</p>
    <p>2 cuillères à soupe de pistaches</p>
  </ingredients>
  <preparation>
  <![CDATA[
    Prévoir 4 heures de réfrigération.
    Faites fondre le chocolat blanc cassé en morceaux dans la crème sur feu doux en remuant avec un fouet.
    Laissez refroidir puis battez les blancs en neige (fermes) en ajoutant le sucre glace en pluie à la fin.Mélangez délicatement les 2 préparations, répartissez-les dans des coupes et mettez-les au frais au moins 4 heures.Décorez de copeaux de chocolat et de pistaches concassées.
    Pour réaliser les copeaux : faites fondre 100 g de chocolat blanc, puis versez-le sur une grande plaque à four tapissée de papier sulfurisé.Après refroidissement, formez les copeaux avec une spatule large. Stockez-les au frais jusqu'au moment de servir.
  ]]>
  </preparation>
</recette>
