<?xml version="1.0" encoding="utf-8"?>
<recette id="73684">
  <titre>Dômes de tomate et saumon</titre>
  <type>Entrée</type>
  <niveau>Très facile</niveau>
  <cout>Moyen</cout>
  <ingredients>
    <p>3 tomates bien fermes</p>
    <p>1/2 poivron rouge</p>
    <p>180 g de dés de saumon fumé</p>
    <p>aneth </p>
    <p>3 feuilles de gélatine</p>
    <p>sel et poivre</p>
    <p>Pour la décoration:</p>
    <p>4 tomates cerise</p>
    <p>aneth</p>
  </ingredients>
  <preparation>
  <![CDATA[
    Ebouillanter les tomates afin de retirer la peau.
    Passer le poivron sous le gril et retirer la peau.
    Faire cuire les légumes coupés en morceaux 10 min dans une casserole, ajouter l'aneth et assaisonner.
    Faire tremper la gélatine dans un peu d'eau.
    Laisser tiédir les légumes puis ajouter le saumon et la gélatine essorée.Mélanger le tout et rectifier l'assaisonnement.
    Verser la préparation dans des moules individuels et mettre au frigo 3 h.Démouler sur assiette et décorer avec une tomate cerise et une petite branche d'aneth.Cette même recette avec 2 cuillères à soupe de fromage blanc et passée au mixer fait un excellent amuse-bouche en verrine. vin blanc sec
  ]]>
  </preparation>
</recette>
