<?xml version="1.0" encoding="utf-8"?>
<recette id="32919">
  <titre>Soupe de potiron aux champignons noirs</titre>
  <type>Entrée</type>
  <niveau>Facile</niveau>
  <cout>Bon marché</cout>
  <ingredients>
    <p>750 g de potiron</p>
    <p>25 cl de crème épaisse</p>
    <p>30 g de beurre</p>
    <p>4/5 champignons noirs</p>
    <p>sel fin</p>
    <p>poivre moulin</p>
    <p>1/2 l de bouillon</p>
  </ingredients>
  <preparation>
  <![CDATA[
    Epluchez et taillez le potiron en dés de 3 cm. 
    Mettez 20 g de beurre dans un faitout chaud, ajoutez le potiron et faites compoter 5 mn sur feu vif en écrasant la pulpe. 
    Ajoutez le bouillon et portez à ébullition puis faites mijoter 15 mn. 
    Rajoutez la crème, mixez à soupe et finir de cuire environ 5 mn. 
    Pendant ce temps faire revenir les champignons noirs émincés très fins dans le reste de beurre. 
    Salez et poivrez et parsemez les assiettes de champignons.
    Essayez cette soupe et vous allez l'adopter. Bon appétit !
  ]]>
  </preparation>
</recette>
