<?xml version="1.0" encoding="utf-8"?>
<recette id="165940">
  <titre>Petite salade d'hiver</titre>
  <type>Entrée</type>
  <niveau>Facile</niveau>
  <cout>Bon marché</cout>
  <ingredients>
    <p>•	1 belle carotte</p>
    <p>•	½ pomme Granny</p>
    <p>•	5 ou 6 feuilles d’endive</p>
    <p>•	1 citron</p>
    <p>•	1 sachet de pignons de pin</p>
    <p>•	huile</p>
    <p>•	sel poivre</p>
  </ingredients>
  <preparation>
  <![CDATA[
    Faites légèrement griller les pignons de pin dans une poêle avec un peu d’huile (de pignon de pin par exemple). Attention, ça va très vite ! Laissez refroidir sur un papier absorbant.
    Epluchez et détaillez la demi pomme en fins bâtonnets. Réservez-les dans un bol d’eau additionnée du jus d’un ½ citron.
    Epluchez et râpez la carotte. Réservez.
    Lavez les feuilles d’endive, taillez-les en lamelles étroites. Réservez.
    Préparez une vinaigrette avec le jus d’un ½ citron, sel, poivre et un peu d’huile.
    Egouttez les bâtonnets de pomme, répartissez-les dans des coupelles individuelles. Confectionnez, par dessus, une couronne de carotte râpée, garnissez le nid ainsi formé de lamelles d’endive. Arrosez le tout de vinaigrette à base de citron pour éviter le noircissement de l’endive et de la pomme.
    Répartissez les pignons de pin grillés sur les salades. Réservez au froid et servez frais.Une petite salade toute simple, vite faite et toute fraîche, pour mettre en appétit. Un blanc sec (type Bourgogne aligoté)
  ]]>
  </preparation>
</recette>
