<?xml version="1.0" encoding="utf-8"?>
<recette id="222899">
  <titre>Scampis sautés aux pommes, sauce crème-curcuma</titre>
  <type>Entrée</type>
  <niveau>Facile</niveau>
  <cout>Bon marché</cout>
  <ingredients>
    <p>15 à 20 scampis</p>
    <p>1 pomme (style jonagold)</p>
    <p>1 citron</p>
    <p>1 cuillère à café de curcuma</p>
    <p>1 1/2 cuillères à café de mascarpone</p>
    <p>1 cuillère à soupe de crème liquide</p>
    <p>vinaigre de cidre</p>
    <p>beurre</p>
    <p>sel</p>
    <p>poivre</p>
  </ingredients>
  <preparation>
  <![CDATA[
    Faire dégeler les scampis s'ils sont surgelés et les déshabiller de leur coquille.
    Peler la pomme et couper en 3/4 en petits dés. Verser du jus du citron pour ne pas que la pomme coupée noircisse.
    Dans une poêle, faire fondre une noix de beurre et y faire revenir à feux doux les pommes. Quand les pommes commencent à dorer, ajouter dans la même poêle les scampis et tourner constamment.
    Saler et poivrer.
    Ajouter 2 traits de vinaigre de cidre, le curcuma, la crème et le mascarpone.
    Laisser cuire à feux doux pendant 10 min sans cesser de remuer pour que les scampis cuisent bien.
    Et voilà, déguster !Personnellement, je fais cette recette en verrines mais je pense qu'elle peut tout à fait convenir pour une entrée ou même en plat, avec du riz basmati.
  ]]>
  </preparation>
</recette>
