<?xml version="1.0" encoding="utf-8"?>
<recette id="95496">
  <titre>Gratin du cousin : citrouille, poivrons, pomme de terre</titre>
  <type>Plat principal</type>
  <niveau>Facile</niveau>
  <cout>Moyen</cout>
  <ingredients>
    <p>700 g de citrouille</p>
    <p>700g de pomme de terre</p>
    <p>3 poivrons ou 1 boite de conserve de 200g de poivrons</p>
    <p>3 gousses d'ail</p>
    <p>4 cuisses de confit de canard</p>
    <p>1 brique de crème fraiche</p>
    <p>sel </p>
    <p>poivre</p>
  </ingredients>
  <preparation>
  <![CDATA[
    Faire cuire les poivrons frais au four 1/2h, les sortir du four, les enrouler dans du papier journal que l'on placera ensuite dans un sac en plastique.
    En attendant, faire cuire les pommes de terre à la vapeur ou à l'eau. Réserver.
    Découper la citrouille en cube pas trop gros, les faire revenir dans un faitout avec l'ail (écrasé) jusqu'à ce que la citrouille s'écrase facilement à la fourchette. Sortir du feu, y mettre les pommes de terre découpées en morceaux. 
    Sortir les poivrons de leur emballage, retirer la peau et découper les en fines lamelles avant de les rajouter à la citrouille + pomme de terre. Mixer le tout en mouillant à la crème fraiche. Assaisonner.
    Dans un plat allant au four, mettre une couche de la purée ainsi faite, la viande des cuisses de canards confites et couvrir du reste de purée.
    On peur mettre en peu de râpé avant d'enfourner à 220°C.La touche originale c'est bel et bien le poivron qui la donne. Sur 3 enfants, on a eu l'unanimité !
  ]]>
  </preparation>
</recette>
