<?xml version="1.0" encoding="utf-8"?>
<recette id="37765">
  <titre>Salade de pâtes aux olives et crevettes</titre>
  <type>Entrée</type>
  <niveau>Très facile</niveau>
  <cout>Bon marché</cout>
  <ingredients>
    <p>500 g de coquillettes </p>
    <p>une boîte d'olives dénoyautées (environ 120 g)</p>
    <p>200 g de petites crevettes cuites (surgelées c'est moins cher)</p>
    <p>3 tomates</p>
    <p>sel et poivre</p>
    <p>huile d'olive à souhait</p>
  </ingredients>
  <preparation>
  <![CDATA[
    Faire cuire les pâtes dans de l'eau bouillante salée.
    Pendant ce temps, couper les tomates et les olives en petits morceaux. Ajouter les crevettes (décongelées et cuites si elles ne l'étaient pas) et assaisonner (sel, poivre, huile).
    Egoutter les pâtes et les passer un moment sous l'eau froide pour arrêter la cuisson. Les ajouter au reste. C'est prêt !
    J'utilise des olives vertes mais c'est bon avec les noires aussi. Cette recette ne paraît pas passionnante à première vue, mais elle vaut le détour... Peut consistuer un repas complet si vous doublez les proportions !
  ]]>
  </preparation>
</recette>
