<?xml version="1.0" encoding="utf-8"?>
<recette id="38703">
  <titre>Tarte Tatin banane chocolat</titre>
  <type>Dessert</type>
  <niveau>Facile</niveau>
  <cout>Bon marché</cout>
  <ingredients>
    <p>250 g de pâte brisée</p>
    <p>4 bananes</p>
    <p>1 jus de citron</p>
    <p>50 g de beurre</p>
    <p>2 sachets de sucre vanillé</p>
    <p>boîte de pastilles de chocolat pour la pâtisserie</p>
  </ingredients>
  <preparation>
  <![CDATA[
    Préchauffez le four à 180°C (thermostat 6). 
    Epluchez les bananes, coupez-les en rondelles et citronnez-les pour qu'elles ne noircissent pas.
    Dans une grande poêle, faites fondre le beurre et le sucre vanillé puis faites soigneusement dorer les rondelles de bananes en veillant à ne pas les écraser.
    Disposez au fond d'un moule à tarte beurré les pastilles de chocolat et les rondelles de bananes dessus sur deux épaisseurs.
    Posez la pâte et enfournez pendant 25 min.
    Comme vous le savez peut-être (ou pas), les tartes tatin se font retournée. C'est pourquoi, il faut mettre les ingrédients avant la pâte.
    Vous pouvez l'accompagner d'une ou deux boules de glace au chocolat noir.A consommer froid.
  ]]>
  </preparation>
</recette>
