<?xml version="1.0" encoding="utf-8"?>
<recette id="28690">
  <titre>Velouté de légumes aux pissenlits</titre>
  <type>Entrée</type>
  <niveau>Très facile</niveau>
  <cout>Bon marché</cout>
  <ingredients>
    <p>500 g de feuilles de pissenlits</p>
    <p>1 oignon</p>
    <p>3 carottes</p>
    <p>3 poireaux</p>
    <p>3 pommes de terre</p>
    <p>30 g de beurre</p>
    <p>1 cube de bouillon de volaille</p>
    <p>2,5 l d'eau</p>
    <p>sel, poivre</p>
  </ingredients>
  <preparation>
  <![CDATA[
    Trier les feuilles de pissenlits et bien les laver pour enlever la terre. 
    Dans une grande marmite, faire fondre le beurre et y faire suer les feuilles de pissenlits et l'oignon émincé. 
    Pendant ce temps trier les autres légumes et les découper en dés pour les carottes et pommes de terres et en fines tranches pour les poireaux. 
    Ajouter les légumes dans la marmite avec les feuilles de pissenlits. 
    Saler, poivrer, ajouter le cube de bouillon de volaille et 2,5 l d'eau. 
    Laisser mijoter pendant environ 30 mn (il faut que les légumes soient bien fondants). 
    Mixer les légumes en rajoutant de l'eau si besoin.
    A servir avec de la crème fraiche et des croûtons.
  ]]>
  </preparation>
</recette>
