<?xml version="1.0" encoding="utf-8"?>
<recette id="41157">
<titre>Velouté de carottes à l'orientale</titre>
<type>Entrée</type>
<niveau>Très facile</niveau>
<cout>Bon marché</cout>
<ingredients>
<p>2 kg de carottes</p>
<p>1 orange</p>
<p>2 pommes</p>
<p>2 cubes de bouillon de légumes</p>
<p>1/2 cuillère à café de cumin en graines</p>
</ingredients>
<preparation>
<operation> eplucher </operation> et <operation ingredients="carottes"> laver </operation> les <ingredient action="laver" quantite="2 kilogramme"> carottes </ingredient> . les <operation> couper </operation> en rondelles d' environ 1 cm et les <operation> mettre </operation> dans une cocotte minute . <operation> eplucher </operation> et <operation ingredients="pommes"> couper </operation> en fines lamelles les 2 <ingredient action="couper" quantite="2"> pommes </ingredient> , <operation ingredients="orange"> presser </operation> l' <ingredient action="presser" quantite="1"> orange </ingredient> pour récolter le <ingredient> jus </ingredient> et <operation> verser </operation> le tout dans la cocotte . <operation ingredients="bouillon;cumin"> ajouter </operation> 1 litre d' eau , 2 cubes de <ingredient action="ajouter"> bouillon </ingredient> de légumes et le <ingredient action="ajouter"> cumin </ingredient> . faire <operation> cuire </operation> 6 min environ à partir du chuchotement de la cocotte . <operation> verser </operation> le tout dans un robot et <operation> mixer </operation> . c' est prêt et c' est dièt ' ! on peut aussi <operation> ajouter </operation> avant de servir pour <operation ingredients="fromage"> agrémenter </operation> quelques miettes de <ingredient action="agrémenter"> fromage </ingredient> de chèvre mi-sec .
</preparation>
</recette>