<?xml version="1.0" encoding="utf-8"?>
<recette id="25919">
<titre>Jambalaya au lard et aux fruits de mer</titre>
<type>Plat principal</type>
<niveau>Facile</niveau>
<cout>Moyen</cout>
<ingredients>
<p>400 g de riz</p>
<p>250 g de lard frais coupé en dés</p>
<p>1 tranche épaisse de jambon de pays coupé en dés</p>
<p>2 pinces des crabes</p>
<p>16 langoustines cuites</p>
<p>24 clams</p>
<p>4 tomates concassées</p>
<p>2 poivrons détaillés en dés</p>
<p>2 oignons hachés</p>
<p>4 gousses d'ail écrasées</p>
<p>2 piments de Cayenne</p>
<p>1 citron vert</p>
<p>1 l de fumet de poisson</p>
<p>huile</p>
<p>thym</p>
<p>1/2 cuillère à soupe de paprika</p>
<p>sel, poivre</p>
</ingredients>
<preparation>
<operation> préparez </operation> tous les éléments comme cités dans les ingrédients . faites <operation ingredients="lardons;huile"> revenir </operation> les <ingredient action="revenir"> lardons </ingredient> dans une grande cocotte avec un peu d' <ingredient action="revenir" quantite=""> huile </ingredient> . <operation ingredients="oignons;ail;poivrons"> ajoutez </operation> les <ingredient action="ajouter" quantite="2"> oignons </ingredient> , l' <ingredient action="ajouter"> ail </ingredient> <operation> écrasées </operation> et les <ingredient action="ajouter"> poivrons </ingredient> . <operation> salez </operation> , <operation> poivrez </operation> et laissez <operation> revenir </operation> . <operation ingredients="riz"> ajoutez </operation> le <ingredient action="ajouter" quantite="400 gramme"> riz </ingredient> , <operation ingredients="thym;tomates;jambon"> saupoudrez </operation> de <ingredient action="saupoudrer" quantite=""> thym </ingredient> et <operation> ajoutez </operation> les piments , les <ingredient action="saupoudrer" quantite="4"> tomates </ingredient> et le <ingredient action="saupoudrer"> jambon </ingredient> . <operation ingredients="citron"> pressez </operation> le <ingredient action="presser" quantite="1"> citron </ingredient> et <operation ingredients="jus"> versez </operation> le <ingredient action="verser"> jus </ingredient> dans la cocotte , <operation ingredients="paprika"> saupoudrez </operation> de <ingredient action="saupoudrer"> paprika </ingredient> et <operation ingredients="poisson"> mouillez </operation> à hauteur de fumet de <ingredient action="mouiller"> poisson </ingredient> . <operation ingredients="crabes;langoustines;clams"> ajoutez </operation> les pinces de <ingredient action="ajouter"> crabes </ingredient> cassées , les <ingredient action="ajouter" quantite="16"> langoustines </ingredient> et les <ingredient action="ajouter" quantite="24"> clams </ingredient> . <operation> couvrez </operation> et laissez <operation> mijoter </operation> environ 30 min à feu doux .
</preparation>
</recette>