<?xml version="1.0" encoding="utf-8"?>
<recette id="25878">
<titre>Truites à la crème d'oseille</titre>
<type>Plat principal</type>
<niveau>Facile</niveau>
<cout>Bon marché</cout>
<ingredients>
<p>6 truites</p>
<p>3 gros oignons</p>
<p>15 g de beurre</p>
<p>1 bouteille de vin blanc sec</p>
<p>450 g d'oseille</p>
<p>60 g de beurre</p>
<p>3 jaunes d'oeufs</p>
<p>150 g de crème fraîche</p>
<p>1 cuillère à soupe de farine</p>
<p>sel et poivre</p>
</ingredients>
<preparation>
préchauffer le four à 200 <operation> ° </operation> c ( thermostat 7 ) . <operation ingredients="oignons"> hacher </operation> les <ingredient action="hacher" quantite="3"> oignons </ingredient> et les faire <operation ingredients="beurre"> fondre </operation> dans le <ingredient action="fondre" quantite="15 gramme+60 gramme"> beurre </ingredient> . <operation> disposer </operation> dans un plat à four et <operation ingredients="truites"> mettre </operation> les <ingredient action="mettre" quantite="6"> truites </ingredient> dessus . <operation> saler </operation> , <operation> poivrer </operation> , <operation ingredients="vin"> arroser </operation> de <ingredient action="arroser"> vin </ingredient> et <operation> couvrir </operation> . <operation> enfourner </operation> pour 15 minutes de cuisson . faire <operation ingredients="oseille;beurre"> fondre </operation> l' <ingredient action="fondre" quantite="450 gramme"> oseille </ingredient> dans le <ingredient action="fondre" quantite="15 gramme+60 gramme"> beurre </ingredient> chaud puis <operation ingredients="farine"> saupoudrer </operation> de <ingredient action="saupoudrer" quantite="1 cuillère à soupe"> farine </ingredient> et <operation> assaisonner </operation> . <operation ingredients="jus"> récuperer </operation> le <ingredient action="récuperer"> jus </ingredient> de cuisson et faire <operation> réduire </operation> de moitié le liquide sur feu vif . <operation ingredients="oeufs"> ajouter </operation> ensuite les jaunes d' <ingredient action="ajouter"> oeufs </ingredient> en <operation ingredients="crème"> fouettant </operation> vivement ainsi que la <ingredient action="fouetter" quantite="150 gramme"> crème </ingredient> . <operation> saler </operation> , <operation> poivrer </operation> . servir les <ingredient quantite="6"> truites </ingredient> avec l' <ingredient quantite="450 gramme"> oseille </ingredient> et la <ingredient quantite="150 gramme"> crème </ingredient> .
</preparation>
</recette>