<?xml version="1.0" encoding="utf-8"?>
<recette id="55970">
<titre>Lapin à la basquaise</titre>
<type>Plat principal</type>
<niveau>Facile</niveau>
<cout>Moyen</cout>
<ingredients>
<p>800 g de découpe de lapin (cuisses, râbles, gigolettes, etc)</p>
<p>2 oignons</p>
<p>1 gousse d'ail</p>
<p>6 tomates pelées ou 1 conserve de 400 g</p>
<p>1 poivron vert</p>
<p>1 poivron rouge</p>
<p>2 courgettes</p>
<p>10 cl de vin blanc</p>
<p>herbes de Provence</p>
<p>sel, poivre</p>
</ingredients>
<preparation>
<operation ingredients="oignons;ail"> découpez </operation> les <ingredient action="découper" quantite="2"> oignons </ingredient> et l' <ingredient action="découper"> ail </ingredient> en lamelles . <operation ingredients="tomates;poivrons"> mettez </operation> dans la cocotte les <ingredient action="mettre" quantite="6"> tomates </ingredient> <operation> pelées </operation> , les <ingredient action="mettre"> poivrons </ingredient> et les courgettes débités en morceaux . <operation ingredients="oignons;ail;vin;sel"> rajoutez </operation> les <ingredient action="rajouter" quantite="2"> oignons </ingredient> , l' <ingredient action="rajouter"> ail </ingredient> , le <ingredient action="rajouter" quantite="10 cl"> vin </ingredient> blanc , une pincée de gros <ingredient action="rajouter" quantite=""> sel </ingredient> et une pincée d' herbes de provence . laissez <operation> cuire </operation> 10 minutes à feu moyen <operation ingredients="lapin"> rajoutez </operation> les morceaux de <ingredient action="rajouter"> lapin </ingredient> , <operation> couvrez </operation> et laissez <operation> cuire </operation> 40 minutes environ . <operation ingredients="assaisonnement"> rectifier </operation> l' <ingredient action="rectifier" quantite="1;;"> assaisonnement </ingredient> selon votre goût en <operation ingredients="sel"> ajoutant </operation> <ingredient action="ajouter" quantite=""> sel </ingredient> et poivre .
</preparation>
</recette>