<?xml version="1.0" encoding="utf-8"?>
<recette id="16774">
<titre>Papillotes de truite</titre>
<type>Plat principal</type>
<niveau>Facile</niveau>
<cout>Bon marché</cout>
<ingredients>
<p>300 g de jardinière de légumes</p>
<p>2 cuillerées de creme fraîche</p>
<p>2 filets de truite</p>
<p>2 noix de beurre</p>
<p>2 grosses pincées d'aneth</p>
<p>2 feuilles d'aluminium</p>
<p>sel et poivre</p>
</ingredients>
<preparation>
<operation ingredients="beurre"> beurrez </operation> le papier d' alu avec le <ingredient action="beurrer"> beurre </ingredient> . <operation ingredients="truites"> posez </operation> dessus les filets de <ingredient action="poser" quantite="2 filet"> truites </ingredient> . <operation ingredients="légumes;truite"> répartissez </operation> les <ingredient action="répartir"> légumes </ingredient> sur les filets de <ingredient action="répartir" quantite="2 filet"> truite </ingredient> , <operation ingredients="crème"> ajoutez </operation> - y la cuillerée de <ingredient action="ajouter"> crème </ingredient> fraîche sur chaque papillote , <operation ingredients="aneth"> saupoudrez </operation> d' <ingredient action="saupoudrer"> aneth </ingredient> , <operation> salez </operation> et <operation> poivrez </operation> modérement . <operation> refermez </operation> les papillotes , <operation> passez </operation> 1 heure au four à thermostat 6 / 180 <operation> ° </operation> c. servez dans ces papillotes .
</preparation>
</recette>