<?xml version="1.0" encoding="utf-8"?>
<recette id="67090">
<titre>Hamburger façon raclette</titre>
<type>Plat principal</type>
<niveau>Très facile</niveau>
<cout>Bon marché</cout>
<ingredients>
<p>4 pains pour hamburgers</p>
<p>1 tomate</p>
<p>1 oignon</p>
<p>8 tranche de fromage à raclette</p>
<p>sauce barbecue</p>
<p>4 steaks hachés (ou escalopes de poulet panées)</p>
<p>4 feilles de laitue ou feuille de chêne</p>
</ingredients>
<preparation>
<operation ingredients="pains"> passer </operation> les <ingredient action="passer" quantite="4"> pains </ingredient> <operation> ouverts </operation> 5 min au four <operation> préchauffé </operation> à thermostat 6 / 7 ( 200 <operation> ° </operation> c ) . faire <operation ingredients="oignon"> revenir </operation> à la <operation> poêle </operation> l' <ingredient action="revenir" quantite="1"> oignon </ingredient> <operation> coupé </operation> finement . faire <operation ingredients="steaks;escalopes"> cuire </operation> les <ingredient action="cuire" quantite="4"> steaks </ingredient> hachés ( ou les <ingredient action="cuire"> escalopes </ingredient> de poulet ) . <operation ingredients="pain"> badigeonner </operation> le <ingredient action="badigeonner" quantite="4"> pain </ingredient> de sauce barbecue . <operation ingredients="salade;tomates;hamburger;fromage"> poser </operation> 1 feuille de <ingredient action="poser"> salade </ingredient> et 2 tranches de <ingredient action="poser" quantite="1"> tomates </ingredient> dans la partie inférieure de chaque <ingredient action="poser"> hamburger </ingredient> , puis une tranche de <ingredient action="poser" quantite="8 tranche"> fromage </ingredient> à raclette . <operation ingredients="oignon;viande"> ajouter </operation> un peu d' <ingredient action="ajouter" quantite="1"> oignon </ingredient> , puis la <ingredient action="ajouter" quantite="8 tranche;4"> viande </ingredient> . <operation ingredients="fromage"> disposer </operation> enfin la 2ème tranche de <ingredient action="disposer" quantite="8 tranche"> fromage </ingredient> raclette , puis <operation ingredients="hamburger"> refermer </operation> le <ingredient action="refermer"> hamburger </ingredient> . <operation ingredients="hamburger"> ecraser </operation> légèrement le <ingredient action="ecraser"> hamburger </ingredient> , puis le <operation> passer </operation> au four 10 à 15 min . vous pouvez servir votre <ingredient> hamburger </ingredient> avec des frites ou pour une version plus " light " avec de la <ingredient> salade </ingredient> .
</preparation>
</recette>