<?xml version="1.0" encoding="utf-8"?>
<recette id="91035">
<titre>Baba aux pamplemousses</titre>
<type>Dessert</type>
<niveau>Facile</niveau>
<cout>Bon marché</cout>
<ingredients>
<p>60 g de farine</p>
<p>25 g de beurre</p>
<p>75 g de sucre</p>
<p>2 cuillères à soupe de lait</p>
<p>2 œufs</p>
<p>Pour le sirop :</p>
<p>2 pamplemousses</p>
<p>50 g de sucre</p>
<p>1 cuillère à café de vanille liquide</p>
</ingredients>
<preparation>
<operation ingredients="œufs;sucre"> mélanger </operation> les jaunes d’ <ingredient action="mélanger" quantite="2"> œufs </ingredient> avec le <ingredient action="mélanger" quantite="75 gramme+50 gramme"> sucre </ingredient> . <operation ingredients="lait;farine;levure"> ajouter </operation> le <ingredient action="ajouter" quantite="2 cuillère à soupe"> lait </ingredient> , la <ingredient action="ajouter" quantite="60 gramme"> farine </ingredient> et la <ingredient action="ajouter"> levure </ingredient> . bien <operation> mélanger </operation> . <operation ingredients="beurre"> ajouter </operation> ensuite le <ingredient action="ajouter"> beurre </ingredient> <operation> fondu </operation> . <operation> monter </operation> les blancs en neige et les <operation> incorporer </operation> délicatement à la préparation . <operation ingredients="pâte"> mettre </operation> la <ingredient action="mettre"> pâte </ingredient> dans des <operation> moules </operation> individuels et faites <operation> cuire </operation> 25 minutes à 180 <operation> ° </operation> c ( thermostat 6 ) . pour le <ingredient> sirop </ingredient> : <operation ingredients="pamplemousses"> presser </operation> les <ingredient action="presser" quantite="2"> pamplemousses </ingredient> . <operation ingredients="jus;sucre"> faites </operation> <operation> bouillir </operation> le <ingredient action="faire"> jus </ingredient> avec le <ingredient action="faire" quantite="75 gramme+50 gramme"> sucre </ingredient> et la vanille . <operation ingredients="gâteau;sirop"> arroser </operation> le <ingredient action="arroser"> gâteau </ingredient> à sa sortie du four avec le <ingredient action="arroser"> sirop </ingredient> .
</preparation>
</recette>