<?xml version="1.0" encoding="utf-8"?>
<recette id="30116">
<titre>Boulettes de mouton et menthe fraîche</titre>
<type>Plat principal</type>
<niveau>Très facile</niveau>
<cout>Bon marché</cout>
<ingredients>
<p>600 g de poitrine de mouton hachée</p>
<p>1 oeuf </p>
<p>1 cuillère à soupe de menthe fraîche hachée </p>
<p>3 cuillères à soupe de farine</p>
<p>4 cuillères à soupe d'huile</p>
<p>sel et poivre</p>
</ingredients>
<preparation>
dans un saladier , <operation ingredients="viande;oeuf;menthe"> placer </operation> la <ingredient action="placer" quantite="600 gramme"> viande </ingredient> , l' <ingredient action="placer" quantite="1"> oeuf </ingredient> et la <ingredient action="placer"> menthe </ingredient> , et <operation> mélanger </operation> le tout . <operation> assaisonner </operation> . réaliser des boulettes de <ingredient quantite="600 gramme"> viande </ingredient> et les <operation> enfariner </operation> . dans une <operation> poêle </operation> ou une sauteuse , faire <operation ingredients="huile"> chauffer </operation> de l' <ingredient action="chauffer" quantite="4 cuillère à soupe"> huile </ingredient> . y <operation> plonger </operation> les boulettes pendant 7 à 8 mn sur chaque face . servir avec du <ingredient> riz </ingredient> , de la purée d' <ingredient> aubergines </ingredient> et des <ingredient> poivrons </ingredient> grillés .
</preparation>
</recette>