<?xml version="1.0" encoding="utf-8"?>
<recette id="15878">
<titre>Gâteau aux macarons</titre>
<type>Dessert</type>
<niveau>Facile</niveau>
<cout>Moyen</cout>
<ingredients>
<p>4 œufs (3 entiers et 1 blanc)</p>
<p>200 g de chocolat fondant</p>
<p>4 dl de crème fraîche</p>
<p>3 cuillères à soupe de café moulu</p>
<p>1,5 dl d'eau bouillante</p>
<p>400 g de macarons durs</p>
<p>4 cuillères à soupe de sucre impalpable (sucre glace)</p>
<p>boudoirs</p>
<p>grains de café en chocolat</p>
<p>1 moule à cake</p>
</ingredients>
<preparation>
faire <operation ingredients="chocolat"> fondre </operation> le <ingredient action="fondre" quantite="200 gramme"> chocolat </ingredient> au bain - marie ( ou au micro-ondes mais alors attention qu' il ne ' <operation> cuise </operation> ' pas ) . <operation ingredients="œufs;café"> ajouter </operation> les jaunes d’ <ingredient action="ajouter" quantite="4"> œufs </ingredient> , l' infusion de <ingredient action="ajouter" quantite="3 cuillère à soupe"> café </ingredient> , <operation> mélanger </operation> et laisser refroidir . <operation ingredients="œufs"> battre </operation> les 4 blancs d’ <ingredient action="battre" quantite="4"> œufs </ingredient> en neige et les <operation ingredients="chocolat"> incorporer </operation> délicatement dans le <ingredient action="incorporer" quantite="200 gramme"> chocolat </ingredient> <operation> fondu </operation> . <operation ingredients="macarons"> réduire </operation> les <ingredient action="réduire" quantite="400 gramme"> macarons </ingredient> en <operation> poudre </operation> . <operation ingredients="crème;sucre"> battre </operation> la <ingredient action="battre" quantite="4 dl"> crème </ingredient> et le <ingredient action="battre" quantite="4 cuillère à soupe"> sucre </ingredient> impalpable . y <operation ingredients="macarons"> ajouter </operation> la <operation> poudre </operation> de <ingredient action="ajouter" quantite="400 gramme"> macarons </ingredient> . <operation> garnir </operation> le <operation> moule </operation> à cake de papier aluminium . <operation ingredients="macarons"> tapisser </operation> les bords du <operation> moule </operation> avec la préparation aux <ingredient action="tapisser" quantite="400 gramme"> macarons </ingredient> ( en garder pour le dessus ) . <operation ingredients="chocolat"> verser </operation> le <operation> mélange </operation> au <ingredient action="verser" quantite="200 gramme"> chocolat </ingredient> . <operation> mettre </operation> au réfrigérateur pendant 1 heure . terminer en tapissant le dessus avec le reste de la préparation aux <ingredient quantite="400 gramme"> macarons </ingredient> et des <ingredient quantite=""> boudoirs </ingredient> . <operation> mettre </operation> au congélateur . sortir du congélateur environ 2 heures avant de servir . <operation> retourner </operation> sur le plat de service , <operation> enlever </operation> le papier d' aluminium et <operation ingredients="café"> garnir </operation> de grains de <ingredient action="garnir" quantite="3 cuillère à soupe"> café </ingredient> en chocolat . c' est extra . je n' ai eu que des compliments sur ce <ingredient quantite="200 gramme;4 dl;4 cuillère à soupe;"> dessert </ingredient> à chaque fois que je l' ai servi !
</preparation>
</recette>