<?xml version="1.0" encoding="utf-8"?>
<recette id="35931">
<titre>Muffins au chocolat noir</titre>
<type>Dessert</type>
<niveau>Très facile</niveau>
<cout>Bon marché</cout>
<ingredients>
<p>3 oeufs </p>
<p>120 g de chocolat noir</p>
<p>20 g de sucre en poudre</p>
<p>30 g de farine</p>
<p>1 sachet de levure</p>
<p>1 sachet de sucre vanillé</p>
<p>1 pincée de sel </p>
<p>30 g de beurre</p>
</ingredients>
<preparation>
<operation> mettre </operation> le four à <operation> préchauffer </operation> à 200 <operation> ° </operation> c ( thermostat 7 ) . en premier <ingredient action="mettre"> lieu </ingredient> , <operation ingredients="lieu;beurre;chocolat"> mettre </operation> le <ingredient action="mettre"> beurre </ingredient> et le <ingredient action="mettre" quantite="120 gramme"> chocolat </ingredient> dans une casserole et <operation> réserver </operation> . <operation ingredients="farine;levure;sucre"> mettre </operation> la <ingredient action="mettre" quantite="30 gramme"> farine </ingredient> , la <ingredient action="mettre" quantite="1 sachet"> levure </ingredient> et le <ingredient action="mettre" quantite="20 gramme+1 sachet"> sucre </ingredient> vanillé dans un autre saladier , bien <operation> mélanger </operation> et <operation> réserver </operation> . ensuite , prendre les <ingredient quantite="3"> oeufs </ingredient> , <operation> séparer </operation> les blancs des jaunes , <operation ingredients="farine;levure;sucre"> incorporer </operation> les jaunes dans le 2ème <operation> mélange </operation> ( <ingredient action="incorporer" quantite="30 gramme"> farine </ingredient> , <ingredient action="incorporer" quantite="1 sachet"> levure </ingredient> et <ingredient action="incorporer" quantite="20 gramme+1 sachet"> sucre </ingredient> vanillé ) . <operation ingredients="sel"> monter </operation> les blancs en neige avec la pincée de <ingredient action="monter" quantite="1 pincée"> sel </ingredient> . lorsque les blancs sont <operation> monté </operation> , <operation ingredients="chocolat;beurre"> mettre </operation> le 1 er <operation> mélange </operation> ( <ingredient action="mettre" quantite="120 gramme"> chocolat </ingredient> et <ingredient action="mettre" quantite="30 gramme"> beurre </ingredient> ) à <operation> chauffer </operation> à feu doux tout en <operation> remuant </operation> régulièrement . <operation ingredients="chocolat"> incorporer </operation> d' abord le <ingredient action="incorporer" quantite="120 gramme"> chocolat </ingredient> <operation> fondant </operation> avec le contenu du saladier et ensuite <operation> mettre </operation> petit à petit les blancs en neiges . <operation> beurrer </operation> des petits <operation> moules </operation> à muffins ( ou un grand <operation> moule </operation> à gâteau ) et y <operation ingredients="pâte"> verser </operation> la <ingredient action="verser"> pâte </ingredient> . baisser le four à 120 <operation> ° </operation> c ( thermostat 4 ) , puis laisser <operation> cuire </operation> 12 minutes . sortir du four et déguster . . . miam ! <ingredient> gâteau </ingredient> ( x ) très facile ( s ) à faire , la seule chose un peu délicate c' est la cuisson car le <ingredient quantite="120 gramme"> chocolat </ingredient> brûle facilement , alors c' est 12 minutes et pas une de plus ! un bon verre de <ingredient> lait </ingredient> ou un <ingredient> thé </ingredient>
</preparation>
</recette>