<?xml version="1.0" encoding="utf-8"?>
<recette id="14734">
<titre>Ramequins au chocolat aux coeurs fondants</titre>
<type>Dessert</type>
<niveau>Très facile</niveau>
<cout>Bon marché</cout>
<ingredients>
<p>100 g de chocolat à pâtisser</p>
<p>8 carrés de chocolat(5 g environ, selon la tablette)</p>
<p>3 oeufs</p>
<p>60 g de beurre</p>
<p>20 g de farine</p>
<p>80 g de sucre</p>
</ingredients>
<preparation>
préchauffez le four à thermostat 8 ( 250 <operation> ° </operation> c ) . faites <operation ingredients="chocolat"> fondre </operation> les 100 g de <ingredient action="fondre" quantite="100 gramme"> chocolat </ingredient> . <operation ingredients="beurre"> ajoutez </operation> le <ingredient action="ajouter" quantite="60 gramme"> beurre </ingredient> . dans un saladier , <operation ingredients="oeufs"> mélangez </operation> les <ingredient action="mélanger" quantite="3"> oeufs </ingredient> , le <ingredient quantite="80 gramme"> sucre </ingredient> et la <ingredient quantite="20 gramme"> farine </ingredient> . <operation ingredients="chocolat"> incorporez </operation> - y le <ingredient action="incorporer" quantite="100 gramme"> chocolat </ingredient> et <operation> mélangez </operation> . <operation> beurrez </operation> et <operation> farinez </operation> les ramequins . <operation> versez </operation> - y le tiers de la préparation , puis <operation ingredients="carrés"> déposez </operation> 2 <ingredient action="déposer" quantite="8"> carrés </ingredient> de chocolat dans chaque ramequin . <operation> recouvrez </operation> du reste de la préparation . <operation> placez </operation> les ramequins au four 10 mn à 15 mn . dégustez les ramequins tièdes , <operation ingredients="non"> démoulés </operation> ou <ingredient action="démouler"> non </ingredient> .
</preparation>
</recette>