<?xml version="1.0" encoding="utf-8"?>
<recette id="27286">
<titre>Petit soufflé léger</titre>
<type>Entrée</type>
<niveau>Très facile</niveau>
<cout>Bon marché</cout>
<ingredients>
<p>1 oeuf</p>
<p>1 pot de 100 g de faisselle Rians</p>
<p>sel, poivre</p>
<p>1 cuiller à café de gélatine en poudre</p>
</ingredients>
<preparation>
<operation> mettre </operation> le four à <operation> chauffer </operation> à 220 <operation> ° </operation> c . <operation ingredients="oeuf;gélatine"> battre </operation> au fouet électrique la faisselle avec le jaune de l' <ingredient action="battre" quantite="1"> oeuf </ingredient> , la <ingredient action="battre"> gélatine </ingredient> , le <ingredient quantite=""> sel </ingredient> , le <ingredient quantite=""> poivre </ingredient> . <operation ingredients="oeuf"> saler </operation> le blanc d' <ingredient action="saler" quantite="1"> oeuf </ingredient> , le <operation> battre </operation> en neige très ferme . <operation ingredients="oeuf"> rajouter </operation> le blance à la préparation faisselle / jaune d' <ingredient action="rajouter" quantite="1"> oeuf </ingredient> . <operation> mettre </operation> dans un plat à soufflet et <operation> enfourner </operation> pour une quinzaine de minutes . vérifier la cuisson et baisser la température du four si le <operation> soufflé </operation> <operation> brunit </operation> trop vite . il est possible de <operation ingredients="fromage;lardons;jambon"> rajouter </operation> à cette préparation du <ingredient action="rajouter"> fromage </ingredient> , des <ingredient action="rajouter"> lardons </ingredient> , du <ingredient action="rajouter"> jambon </ingredient> , etc. plat qui peut à la fois servir d' entrée ou de plat de résistance <operation ingredients="salade"> accompagné </operation> d' une <ingredient action="accompagner"> salade </ingredient> pour un repas léger . rosé léger
</preparation>
</recette>