<?xml version="1.0" encoding="utf-8"?>
<recette id="26007">
<titre>Flan aux girolles</titre>
<type>Entrée</type>
<niveau>Facile</niveau>
<cout>Moyen</cout>
<ingredients>
<p>250 g de girolles</p>
<p>3 oeufs</p>
<p>20 g de gruyère râpé</p>
<p>100 g de fromage blanc maigre</p>
<p>2 échalotes hachées</p>
<p>1 cuillère à café de ketchup</p>
<p>1 pincée de noix de muscade</p>
<p>10 g de maïzena</p>
<p>1 cuillère à soupe de fines herbes</p>
<p>quelques feuilles de laitue</p>
<p>sel, poivre</p>
<p>papier aluminium</p>
<p>1 moule à tarte à fond amovible</p>
</ingredients>
<preparation>
<operation> nettoyer </operation> , <operation> peler </operation> et <operation ingredients="girolles"> essuyer </operation> les <ingredient action="essuyer" quantite="250 gramme"> girolles </ingredient> à l' aide d' un linge propre ou de papier absorbant , puis les <operation> détailler </operation> en quartiers . dans une <operation> poêle </operation> anti-adhésive , les faire <operation ingredients="échalotes"> revenir </operation> avec les <ingredient action="revenir" quantite="2"> échalotes </ingredient> hachées . <operation ingredients="sel;poivre;noix"> assaisonner </operation> en saupoudrant le tout de <ingredient action="assaisonner" quantite=""> sel </ingredient> , <ingredient action="assaisonner" quantite=""> poivre </ingredient> et d' une pincée de <ingredient action="assaisonner" quantite="1 pincée"> noix </ingredient> de muscade . laisser <operation> mijoter </operation> à feu très doux à <operation> couvert </operation> pendant 10 min environ puis les <operation> réserver </operation> au chaud . <operation> préchauffer </operation> votre four à 180 <operation> ° </operation> c ( thermostat 6 ) . <operation> séparer </operation> les jaunes des blancs puis les <operation> disposer </operation> dans 2 saladiers distincts . <operation ingredients="fromage;maïzena;ketchup;gruyère"> battre </operation> les jaunes avec le <ingredient action="battre" quantite="100 gramme"> fromage </ingredient> blanc , la <ingredient action="battre" quantite="10 gramme"> maïzena </ingredient> , le <ingredient action="battre" quantite="1 cuillère à café"> ketchup </ingredient> et le <ingredient action="battre" quantite="20 gramme"> gruyère </ingredient> . <operation> monter </operation> les blancs en neige très ferme . <operation> mélanger </operation> les 2 préparations pour obtenir une <ingredient> crème </ingredient> onctueuse . <operation> recouvrir </operation> un <operation> moule </operation> à tarte à fond amovible d' une feuille de papier d' aluminium , puis y <operation ingredients="crème;oeufs;fromage"> verser </operation> la moitié de la <ingredient action="verser"> crème </ingredient> aux <ingredient action="verser" quantite="3"> oeufs </ingredient> et au <ingredient action="verser" quantite="100 gramme"> fromage </ingredient> blanc . <operation> enfourner </operation> et laisser <operation> cuire </operation> 5 à 10 min à four chaud . sortir le <operation> moule </operation> du four et y <operation ingredients="girolles"> incorporer </operation> les <ingredient action="incorporer" quantite="250 gramme"> girolles </ingredient> <operation ingredients="herbes"> saupoudrées </operation> de fines <ingredient action="saupoudrer" quantite="1 cuillère à soupe"> herbes </ingredient> . terminer par une couche du <operation> mélange </operation> aux <ingredient quantite="3"> oeufs </ingredient> qui reste . replacer au four 10 min , <operation> enlever </operation> le tour du <operation> moule </operation> en ne gardant que le fond avec la préparation . <operation> ôter </operation> ensuite la feuille de papier d' aluminium , puis <operation> dresser </operation> sur un plat <operation ingredients="laitue"> recouvert </operation> de feuilles de <ingredient action="recouvrir" quantite="quelque feuille"> laitue </ingredient> .
</preparation>
</recette>