<?xml version="1.0" encoding="utf-8"?>
<recette id="11857">
<titre>Rougets en papillotte sans matière grasse</titre>
<type>Plat principal</type>
<niveau>Moyennement difficile</niveau>
<cout>Moyen</cout>
<ingredients>
<p>4 filets de rouget</p>
<p>15 cl de vin blanc sec</p>
<p>1 citron</p>
<p>Pour les herbes :</p>
<p>herbes de Provence</p>
<p>persil</p>
<p>aneth...</p>
<p>20 cl de crème allégée</p>
</ingredients>
<preparation>
faire <operation ingredients="vin;jus"> mariner </operation> les filets dans le <ingredient action="mariner" quantite="15 cl"> vin </ingredient> blanc , le <ingredient action="mariner"> jus </ingredient> du citron et les herbes pendant au moins 1 heure . <operation ingredients="rougets"> egoutter </operation> les <ingredient action="egoutter"> rougets </ingredient> . <operation> mettre </operation> dans les papillotes 2 filets et une cuillère à soupe de marinade . <operation> refermer </operation> . <operation> passer </operation> à four moyen ( 180 <operation> ° </operation> c / thermostat 6 ) pour que la marinade ne s' évapore pas trop vite et que les filets ne sèchent pas . pour servir , <operation ingredients="crème"> mélanger </operation> la <ingredient action="mélanger" quantite="20 cl"> crème </ingredient> allégée avec le reste de la marinade . servir avec du <ingredient> riz </ingredient> sauvage , des <ingredient> pommes </ingredient> de terre vapeur ou des <ingredient> pâtes </ingredient> fraîches .
</preparation>
</recette>