<?xml version="1.0" encoding="utf-8"?>
<recette id="195808">
<titre>La charlotte : recette de base à toutes les variantes</titre>
<type>Dessert</type>
<niveau>Moyennement difficile</niveau>
<cout>Bon marché</cout>
<ingredients>
<p>2 paquets de boudoirs ou biscuits à la cuillère (en prévoir 3 suivant la taille du moule)</p>
<p>50 cl de crème entière liquide</p>
<p>2 sachets de "fix chantilly"</p>
<p>30 g de sucre glace</p>
<p>Fruits / arômes / épices, au choix</p>
<p>15 cl de sirop de votre préparation (à base de sirop sucré léger + jus de fruits ou alcool...)</p>
<p>Pour la charlotte au chocolat : 1/2 tablette de chocolat pâtissier + 3 blancs d'oeuf)</p>
</ingredients>
<preparation>
la base de la charlotte est <operation ingredients="biscuits;mousse"> composée </operation> de <ingredient action="composer"> biscuits </ingredient> , d' un appareil aéré de type <ingredient action="composer"> mousse </ingredient> ou chantilly , et de la garniture de votre choix . tout est possible ! préparation de la <ingredient quantite="50 cl"> crème </ingredient> : <operation ingredients="crème"> mettre </operation> la <ingredient action="mettre" quantite="50 cl"> crème </ingredient> liquide , le saladier et le fouet au congélateur 30 min max avant . <operation ingredients="crème;épices"> verser </operation> la <ingredient action="verser" quantite="50 cl"> crème </ingredient> dans le saladier , <operation ingredients="chantilly"> ajouter </operation> 1 sachet de fix <ingredient action="ajouter"> chantilly </ingredient> et le <ingredient quantite="30 gramme"> sucre </ingredient> <ingredient> glace </ingredient> ( à <operation> ajuster </operation> selon vos goûts ) , et les éventuels <ingredient action="verser"> épices </ingredient> / arômes que vous aurez <operation> choisi </operation> . <operation ingredients="chantilly"> battre </operation> pendant au moins 3 min sans cesser , tout en <operation> rajoutant </operation> au fur et à <operation> mesure </operation> le 2ème sachet de fix <ingredient action="battre"> chantilly </ingredient> . arrêter de <operation> battre </operation> quand la <ingredient quantite="50 cl"> crème </ingredient> est figée , bien ferme . pour la charlotte au <ingredient> chocolat </ingredient> : <operation ingredients="mousse"> faire </operation> une <ingredient action="faire"> mousse </ingredient> . faire <operation ingredients="chocolat"> fondre </operation> le <ingredient action="fondre"> chocolat </ingredient> , y <operation ingredients="œufs"> intégrer </operation> les 3 blancs d' <ingredient action="intégrer"> œufs </ingredient> <operation> battus </operation> en neige ferme . pour les <ingredient> biscuits </ingredient> : <operation ingredients="biscuits;sirop"> tremper </operation> les <ingredient action="tremper"> biscuits </ingredient> sur 1 face , pendant 1 seconde dans le <ingredient action="tremper" quantite="15 cl"> sirop </ingredient> de votre choix . <operation> recouvrir </operation> un <operation> moule </operation> à charlotte de film alimentaire en laissant largement dépasser sur les bords . <operation ingredients="biscuits"> disposer </operation> les <ingredient action="disposer"> biscuits </ingredient> sur le pourtour du <operation> moule </operation> en les serrant assez , ainsi que dans le fond ( <operation ingredients="biscuits"> couper </operation> les <ingredient action="couper"> biscuits </ingredient> s' ils dépassent ) . pour le montage : alterner couches de <ingredient quantite="50 cl"> crème </ingredient> <ingredient> chantilly </ingredient> , de <ingredient quantite=""> fruits </ingredient> <operation> pelés </operation> et <operation> coupés </operation> en morceaux , et de <ingredient> biscuits </ingredient> légèrement <operation> imbibés </operation> , en terminant par une couche de <ingredient> biscuits </ingredient> ( <operation> découper </operation> ceux qui dépassent ) . <operation> rabattre </operation> le film sur la charlotte <operation> poser </operation> une assiette dessus , et <operation> mettre </operation> au frais pour 6 h minimum . pour la présentation : <operation> démouler </operation> la charlotte sur une assiette en la <operation> retournant </operation> . <operation> décorer </operation> le dessus en utilisant le reste de <ingredient> chantilly </ingredient> avec une <operation> poche </operation> à douille , ou en <operation ingredients="fruit;chocolat"> disposant </operation> une rosace de <ingredient action="disposer" quantite=""> fruit </ingredient> , ou encore des copeaux de <ingredient action="disposer"> chocolat </ingredient> . et régalez -vous ! une charlotte c' est la garantie d' un <ingredient quantite="50 cl;30 gramme;15 cl"> dessert </ingredient> inratable , peu coûteux , qui s' improvise avec n' importe quel <ingredient quantite=""> fruit </ingredient> , mais aussi d' un succès à table ! pensez à la version <operation> salée </operation> avec <ingredient quantite="50 cl"> légumes </ingredient> grillés , <ingredient> épices </ingredient> et aromates . . . idées de garniture . <ingredient> poire </ingredient> - mousse <ingredient> chocolat </ingredient> , ananas / vanille , <ingredient> fraise </ingredient> / kiwi , mousse de citron / pomme verte , <ingredient quantite=""> fruits </ingredient> rouges , <ingredient> pommes </ingredient> caramélisées / <ingredient> cannelle </ingredient> , pêche / abricot , 3 <ingredient> chocolats </ingredient> ( 3 <ingredient> mousses </ingredient> différentes ) , <ingredient> mousse </ingredient> <ingredient> chocolat </ingredient> / oranges <ingredient> confites </ingredient> .
</preparation>
</recette>