<?xml version="1.0" encoding="utf-8"?>
<recette id="57879">
<titre>Paupiettes de veau aux pruneaux et aux lardons</titre>
<type>Plat principal</type>
<niveau>Très facile</niveau>
<cout>Moyen</cout>
<ingredients>
<p>4 escalopes de veau</p>
<p>16 gros pruneaux</p>
<p>2 oignons, 1 gousse d'ail</p>
<p>100 g de lardons fumés</p>
<p>15 cl de bouillon</p>
<p>15 cl de vin blanc sec</p>
<p>1 cuillère d'huile, 30 g de beurre</p>
<p>sel, poivre</p>
</ingredients>
<preparation>
<operation ingredients="escalopes"> saler </operation> et <operation> poivrer </operation> les <ingredient action="saler" quantite="4"> escalopes </ingredient> sur chaque face . <operation ingredients="pruneaux"> dénoyauter </operation> 8 <ingredient action="dénoyauter" quantite="16"> pruneaux </ingredient> , <operation ingredients="pruneaux;escalope"> déposer </operation> 2 <ingredient action="déposer" quantite="16"> pruneaux </ingredient> sur chaque <ingredient action="déposer" quantite="4"> escalope </ingredient> , les <operation> rouler </operation> et les <operation> ficeler </operation> . <operation ingredients="oignons"> hacher </operation> finement les <ingredient action="hacher" quantite="2"> oignons </ingredient> , <operation ingredients="ail"> écraser </operation> l' <ingredient action="écraser"> ail </ingredient> sans l' <operation> éplucher </operation> . dans une cocotte faire <operation ingredients="beurre;huile"> fondre </operation> le <ingredient action="fondre" quantite="30 gramme"> beurre </ingredient> et l' <ingredient action="fondre" quantite="1 cuillère"> huile </ingredient> , <operation> mettre </operation> à <operation ingredients="paupiettes;lardons"> dorer </operation> les <ingredient action="dorer"> paupiettes </ingredient> et les <ingredient action="dorer"> lardons </ingredient> , <operation> réserver </operation> le tout , <operation ingredients="oignons"> cuire </operation> à petit feu les <ingredient action="cuire" quantite="2"> oignons </ingredient> ( ils doivent être translucide ) , <operation ingredients="ail"> ajouter </operation> l' <ingredient action="ajouter"> ail </ingredient> puis <operation ingredients="vin"> déglacer </operation> avec le <ingredient action="déglacer" quantite="15 cl"> vin </ingredient> blanc , <operation> porter </operation> à <operation> ébullition </operation> , <operation ingredients="bouillon;paupiettes"> ajouter </operation> le <ingredient action="ajouter" quantite="15 cl"> bouillon </ingredient> et les <ingredient action="ajouter"> paupiettes </ingredient> . <operation> couvrir </operation> , laisser <operation> mijoter </operation> 45 min . <operation ingredients="pruneaux"> ajouter </operation> les 8 <ingredient action="ajouter" quantite="16"> pruneaux </ingredient> restant à mi-cuisson . 10 min avant la fin de cuisson <operation> réduire </operation> la sauce si nécessaire , <operation ingredients="assaisonnement"> rectifier </operation> l' <ingredient action="rectifier" quantite="1;1 cuillère;;"> assaisonnement </ingredient> , servir chaud ! nous dégustons cette recette avec du <ingredient> riz </ingredient> tout simplement !
</preparation>
</recette>