<?xml version="1.0" encoding="utf-8"?>
<recette id="56087">
<titre>Scampis au beurre d'ail de tante maggy</titre>
<type>Plat principal</type>
<niveau>Très facile</niveau>
<cout>Moyen</cout>
<ingredients>
<p>400 g de scampis</p>
<p>une grosse cuillère à soupe de beurre</p>
<p>ciboulette</p>
<p>persil</p>
<p>une gousse d'ail</p>
<p>une échalote</p>
<p>une tomate</p>
<p>sel et poivre</p>
<p>15 cl de crème fraîche légère</p>
</ingredients>
<preparation>
<operation ingredients="beurre;gousse;ciboulette;persil;sel;poivre"> préparer </operation> le <ingredient action="préparer"> beurre </ingredient> d' ail avec la cuillère à soupe de beurre , la <ingredient action="préparer" quantite="1"> gousse </ingredient> d' ail <operation> hachée </operation> , assez bien de <ingredient action="préparer" quantite=""> ciboulette </ingredient> et de <ingredient action="préparer"> persil </ingredient> , le <ingredient action="préparer" quantite=""> sel </ingredient> et le <ingredient action="préparer"> poivre </ingredient> . <operation ingredients="échalote"> hacher </operation> l' <ingredient action="hacher" quantite="1"> échalote </ingredient> et faites <operation ingredients="scampis"> revenir </operation> dans une poele avec les <ingredient action="revenir" quantite="400 gramme"> scampis </ingredient> préalablement <operation ingredients="huile"> décortiqués </operation> dans un tout petit peu d' <ingredient action="décortiquer"> huile </ingredient> , histoire que ca ne <operation> colle </operation> pas . quand les <ingredient> crevettes </ingredient> sont bien rosées , <operation ingredients="beurre;tomate"> rajouter </operation> le <ingredient action="rajouter"> beurre </ingredient> d' ail avec la <ingredient action="rajouter" quantite="1"> tomate </ingredient> <operation> coupée </operation> en petits morceaux . lorsque la <ingredient quantite="1"> tomate </ingredient> est bien cuite , <operation ingredients="crème"> rajouter </operation> alors la <ingredient action="rajouter" quantite="15 cl"> crème </ingredient> fraîche , laisser <operation> cuire </operation> encore quelques minutes et c' est prêt .
</preparation>
</recette>