<?xml version="1.0" encoding="utf-8"?>
<recette id="69153">
<titre>Moules à la crème super faciles</titre>
<type>Plat principal</type>
<niveau>Très facile</niveau>
<cout>Bon marché</cout>
<ingredients>
<p>4 kg de moules</p>
<p>20 cl de crème liquide</p>
<p>2 gros oignons</p>
<p>1 bouquet garni</p>
</ingredients>
<preparation>
<operation> préparer </operation> les <operation> moules </operation> en les <operation> frottant </operation> contre une éponge métallique ( propre ! ) ou bien les <operation ingredients="couteau"> gratter </operation> avec un <ingredient action="gratter"> couteau </ingredient> . <operation> eplucher </operation> les <ingredient action="faire" quantite="2"> oignons </ingredient> , les <operation ingredients="oignons"> faire </operation> légèrement <operation> blanchir </operation> dans une cocotte . <operation ingredients="bouquet"> ajouter </operation> les <operation> moules </operation> puis le <ingredient action="ajouter" quantite="1"> bouquet </ingredient> <operation> garni </operation> . <operation> mélanger </operation> deux ou trois fois pendant la cuisson . la cuisson est terminée lorsque les <operation> moules </operation> sont ouvertes . <operation ingredients="crème"> verser </operation> la <ingredient action="verser" quantite="20 cl"> crème </ingredient> liquide en fin de cuisson et laisser <operation> cuire </operation> encore 5 minutes . excellent ! ! ! pas de <ingredient> vin </ingredient> blanc de <operation> cuisine </operation> . . . comme ça si vous en avez pas sous la main . . . et c' est aussi bon . . . un régal ! ! ! un ptit <ingredient> vin </ingredient> blanc ! ! !
</preparation>
</recette>